GeoHD/AKDE.py
GeoHD/__init__.py
GeoHD/analyze.py
GeoHD/process.py
GeoHD/utils.py
GeoHD/visualize.py
GeoHD/zone.py
test/__init__.py
GeoHD-0.1.5.dist-info/LICENSE
GeoHD-0.1.5.dist-info/METADATA
GeoHD-0.1.5.dist-info/WHEEL
GeoHD-0.1.5.dist-info/top_level.txt
GeoHD-0.1.5.dist-info/RECORD
